pgtuner_mcp/__init__.py
pgtuner_mcp/__main__.py
pgtuner_mcp/server.py
pgtuner_mcp/services/__init__.py
pgtuner_mcp/services/hypopg_service.py
pgtuner_mcp/services/index_advisor.py
pgtuner_mcp/services/sql_driver.py
pgtuner_mcp/services/user_filter.py
pgtuner_mcp/tools/__init__.py
pgtuner_mcp/tools/toolhandler.py
pgtuner_mcp/tools/tools_bloat.py
pgtuner_mcp/tools/tools_health.py
pgtuner_mcp/tools/tools_index.py
pgtuner_mcp/tools/tools_performance.py
pgtuner_mcp/tools/tools_vacuum.py
pgtuner_mcp-0.5.2.dist-info/licenses/LICENSE
pgtuner_mcp-0.5.2.dist-info/METADATA
pgtuner_mcp-0.5.2.dist-info/WHEEL
pgtuner_mcp-0.5.2.dist-info/entry_points.txt
pgtuner_mcp-0.5.2.dist-info/top_level.txt
pgtuner_mcp-0.5.2.dist-info/RECORD
