Metadata-Version: 2.4
Name: pgtuner_mcp
Version: 0.5.2
Summary: An MCP server for PostgreSQL AI-powered performance tuning with HypoPG support
Author-email: DanielShih <dog830228@gmail.com>
Project-URL: Source, https://github.com/isdaniel/pgtuner_mcp
Requires-Python: >=3.10
License-File: LICENSE
Requires-Dist: mcp[cli]>=1.12.0
Requires-Dist: psycopg[binary,pool]>=3.1.0
Requires-Dist: pglast>=7.10
Provides-Extra: sse
Requires-Dist: starlette>=0.27.0; extra == "sse"
Requires-Dist: uvicorn>=0.23.0; extra == "sse"
Provides-Extra: dev
Requires-Dist: pytest>=9.0.1; extra == "dev"
Requires-Dist: pytest-asyncio>=1.3.0; extra == "dev"
Requires-Dist: pytest-cov>=7.0.0; extra == "dev"
Requires-Dist: ruff>=0.1.0; extra == "dev"
Dynamic: license-file
